eve_models/__init__.py
eve_models/apps.py
eve_models/organization.py
eve_models/worflow.py
common_models-0.0.6.dist-info/METADATA
common_models-0.0.6.dist-info/WHEEL
common_models-0.0.6.dist-info/top_level.txt
common_models-0.0.6.dist-info/RECORD
