Metadata-Version: 2.1
Name: common-models
Version: 0.0.6
Summary: A package containing common Django eve_models
Home-page: https://github.com/evercycle-org/common_models
Requires-Dist: django >=4.0
